fast_abstract/__init__.py
fast_abstract/core.py
fast_abstract-0.1.0.dist-info/METADATA
fast_abstract-0.1.0.dist-info/WHEEL
fast_abstract-0.1.0.dist-info/top_level.txt
fast_abstract-0.1.0.dist-info/RECORD
