Metadata-Version: 2.1
Name: fast_abstract
Version: 0.1.0
Summary: A high-performance abstract base class implementation for Python
Home-page: https://github.com/mavin2009/fast_abstract
Author: Michael Avina
Author-email: a.v.i.na.m@gm-ail.com
License: MIT
Classifier: Programming Language :: Python :: 3
Classifier: License :: OSI Approved :: MIT License
Classifier: Operating System :: OS Independent
Requires-Python: >=3.6
